{
  "navbar": {
    "products": "Products",
    "services": "Services",
    "references": "References",
    "about": "About Us",
    "blog": "Blog",
    "contact_btn": "Contact",
    "quote_btn": "Request a Quote",
    "mega_menu": {
      "categories": {
        "title": "Categories",
        "links": [
          { "name": "Wooden Playgrounds", "href": "/termekek/fa-jatszoterek" },
          { "name": "Metal Playgrounds", "href": "/termekek/fem-jatszoterek" },
          { "name": "Swings", "href": "/termekek/hintak" },
          { "name": "Outdoor Fitness", "href": "/termekek/kulteri-fitnesz" },
          { "name": "Spring Riders", "href": "/termekek/rugos-jatekok" },
          { "name": "Street Furniture", "href": "/termekek/utcabutorok" }
        ]
      },
      "featured": {
        "title": "Featured Offers",
        "links": [
          { "name": "Discounted Products", "href": "/termekek/akcio" },
          { "name": "New Arrivals", "href": "/termekek/ujdonsagok" }
        ]
      },
      "recent_posts_title": "Fresh From the Blog"
    },
    "top_bar": {
      "phone": "+36 70 369-8193",
      "email": "info@terrafortebau.hu",
      "address": "Hungary, 3662 Ózd-Somsályfő Telep 1.",
      "marketing_text": "Standard-Compliant Manufacturing • 30 Years of Experience",
      "social_aria": "Follow us",
      "call_us": "Call us:"
    }
  },
  "Footer": {
    "copyright": "© {year} Terra Forte Bau Kft. All rights reserved.",
    "newsletter": {
      "title": "Subscribe to Our Newsletter",
      "description": "Don't miss out on grant opportunities, latest news, and professional articles. Sent monthly.",
      "placeholder": "Enter your email address",
      "button": "Subscribe"
    },
    "marketing_text": "Manufacturing and comprehensive construction of EU-standard public playgrounds for municipalities and institutions.",
    "sections": {
      "products": {
        "title": "Our Products",
        "links": [
          { "name": "Climbing Frames", "href": "/termekek/maszokak" },
          { "name": "Swings", "href": "/termekek/hintak" },
          { "name": "Slides", "href": "/termekek/csuszdak" },
          { "name": "Complete Sets", "href": "/termekek/szettek" },
          { "name": "Street Furniture", "href": "/termekek/utcabutorok" }
        ]
      },
      "support": {
        "title": "Support",
        "links": [
          { "name": "Contact", "href": "/kapcsolat" },
          { "name": "FAQ", "href": "/gyik" },
          { "name": "Installation Guides", "href": "/telepites" },
          { "name": "Document Library", "href": "/letoltesek" }
        ]
      },
      "company": {
        "title": "Our Company",
        "links": [
          { "name": "About Us", "href": "/rolunk" },
          { "name": "References", "href": "/referenciak" },
          { "name": "Blog", "href": "/blog" },
          { "name": "Career", "href": "/karrier" }
        ]
      },
      "legal": {
        "title": "Legal",
        "links": [
          { "name": "Privacy Policy", "href": "/adatvedelem" },
          { "name": "Imprint", "href": "/impresszum" }
        ]
      }
    }
  },
  "HomePage": {
    "Hero": {
      "badge_text": "European Production & Warranty",
      "badge_link": "Learn more about us",
      "title": "Design & Construction of EU-Standard Playgrounds",
      "subtitle": "Safe community spaces for municipalities and institutions. Comprehensive management from design to TÜV certification.",
      "cta_references": "View Our References",
      "cta_contact": "Free Site Survey"
    },
    "USP": {
      "section_title": "Why Choose Terra Forte Bau?",
      "section_subtitle": "Building timeless community spaces with over 30 years of experience.",
      "standard": "MSZ EN 1176 Standard",
      "standard_desc": "All our equipment holds the necessary TÜV certification and complies with European standards.",
      "premium": "Domestic Manufacturing Background",
      "premium_desc": "Our in-house carpentry and metalworking workshops guarantee premium quality and fast spare parts supply.",
      "full_service": "Turnkey Solution",
      "full_service_desc": "We take the burden off your shoulders: groundwork, manufacturing, installation, and shock absorption from a single source."
    },
    "Categories": {
      "section_title": "Explore Categories",
      "browse_all": "View All Categories",
      "items": {
        "wooden": {
          "title": "Wooden Playgrounds",
          "cta": "View"
        },
        "metal": {
          "title": "Metal Playgrounds",
          "cta": "View"
        },
        "fitness": {
          "title": "Outdoor Fitness",
          "cta": "View"
        }
      }
    },
    "Newsletter": {
      "title": "Don't miss out on grant opportunities and the latest news!",
      "placeholder": "Enter your email address",
      "button": "Subscribe",
      "privacy_text": "We handle your data confidentially. Read our",
      "privacy_link_text": "Privacy Policy."
    },
    "FeaturedReferences": {
      "title": "Our Pride: Installed Playgrounds",
      "subtitle": "Over 500+ successful projects nationwide.",
      "description": "Whether it's a municipal public space, a kindergarten yard, or a residential park, our references prove our expertise. View our past works and get inspired for your own project.",
      "cta": "View All References"
    },
    "Partners": {
      "title": "Certifications & Professional Background",
      "subtitle": "Our quality is guaranteed by the strictest standards and our domestic manufacturing background.",
      "items": [
        {
          "name": "TÜV Rheinland",
          "logo": "/Partners/tuv.svg",
          "description": "Certified Safety"
        },
        {
          "name": "Magyar Falu Program",
          "logo": "/Partners/mfp.png",
          "description": "Grant Application Expert"
        },
        {
          "name": "MSZ EN 1176",
          "logo": "/Partners/msz.png",
          "description": "Standard-Compliant Manufacturing"
        },
        {
          "name": "MKIK",
          "logo": "/Partners/mkik.png",
          "description": "Registered Contractor"
        },
        {
          "name": "Domestic Manufacturing",
          "logo": "/Partners/hungary.png",
          "description": "100% Hungarian Enterprise"
        }
      ]
    },
    "ServicesSection": {
      "badge": "Full-Service Implementation",
      "title": "From Design to Turnkey Delivery",
      "description": "We don't just manufacture equipment; we take the burden off your shoulders. Our expert team coordinates every step of the process so you only need to attend the handover.",
      "features": [
        {
          "name": "Custom Design.",
          "description": "We create visual plans based on on-site surveys, considering safety zones and budget constraints."
        },
        {
          "name": "Premium Manufacturing.",
          "description": "We manufacture certified equipment in our own facility using selected wood and metal materials with CNC technology."
        },
        {
          "name": "Professional Installation.",
          "description": "Our own installation team handles concreting, impact-absorbing surfacing, and equipment fixation."
        }
      ],
      "cta_services": "Our Services in Detail"
    },
    "WhyChooseUs": {
      "title": "We Are Partners in Community Development",
      "description": "We know that building a playground is a serious responsibility. Our expert team guides you through the entire process.",
      "features": [
        {
          "title": "Domestic Expertise & Reliability",
          "description": "As a Hungarian-owned business with over 30 years of experience, we understand local needs and standards. Personal connection and trust come first for us."
        },
        {
          "title": "Strict Safety Compliance",
          "description": "Every device we manufacture and install holds the necessary MSZ EN 1176 certification. For us, children's safety is not an option, but a fundamental requirement."
        },
        {
          "title": "Full Customizability",
          "description": "We offer more than just catalog products. Our flexible manufacturing technology allows us to tailor the playground to the specific site and budget."
        },
        {
          "title": "Grant Application Experience",
          "description": "We are familiar with the requirements of Hungarian grant systems. We assist with everything from technical documentation to mandatory administration."
        }
      ]
    },
    "CtaSection": {
      "title": "Ready to design the perfect playground?",
      "subtitle": "Request a free on-site assessment and personalized quote from our experts!",
      "primary_btn": "Get a Free Quote",
      "secondary_btn": "View References"
    }
  },
  "AboutPage": {
    "Hero": {
      "title": "Leadership Expertise Since 1996: Your Reliable Playground Manufacturing Partner!",
      "subtitle": "Terra Forte Bau is the reliable manufacturer and partner whose management has been an active player in the playground market since 1996. This professional experience of more than a quarter of a century guarantees that your community spaces meet the highest quality and safety standards. We manufacture a wide range of wooden and metal playground equipment ourselves, ensuring full control over quality from design to final construction.",
      "cta": "Contact Us"
    },
    "Stats": {
      "title": "Reliability in Numbers",
      "subtitle": "We are proud of our achievements and the trust of our partners.",
      "items": [
        {
          "label": "Years of Professional Experience",
          "value": "30+"
        },
        {
          "label": "Successfully Delivered Playgrounds",
          "value": "500+"
        },
        {
          "label": "Hungarian Ownership",
          "value": "100%"
        },
        {
          "label": "Product Warranty",
          "value": "5 Years"
        }
      ]
    },
    "Mission": {
      "title_part1": "Design, Consultancy.",
      "title_highlight": "Grants.",
      "subtitle": "The in-depth professional knowledge of Terra Forte Bau's management, accumulated since 1996, primarily serves the success of public projects. We are not just a playground manufacturer, but also the professional consultant for your investment:",
      "description": {
        "features": [
          "Grant Advantage: Our priority service is supporting municipalities and public institutions in preparing the technical part of grant applications. We write professional plans and budgets, greatly easing your administrative workload.",
          "Design Expertise: As a manufacturer, we assist in preparing EU-standard wooden and metal playground plans tailored to local conditions.",
          "Comprehensive Quality: Our manufacturing background ensures quality, while professional consultancy ensures the legal and financial success of the investment."
        ]
      }
    },
    "Values": {
      "title": "Our Core Values",
      "subtitle": "These are the pillars upon which we build every project.",
      "items": [
        {
          "name": "Safety Above All",
          "description": "We make no compromises when it comes to children. All our equipment meets the strictest MSZ EN 1176 standards."
        },
        {
          "name": "Innovative Materials",
          "description": "UV-stable plastics, CNC-machined elements, and weather-resistant treatments ensure long durability."
        },
        {
          "name": "Community Building",
          "description": "Our goal is not just to install equipment, but to create spaces where families and communities can meet."
        }
      ]
    },
    "MaterialTypes": {
      "title": "Wood and Metal Playgrounds",
      "subtitle": "Terra Forte Bau's strength lies in its dual production line, satisfying both traditional and modern needs.",
      "wood": {
        "title": "Wooden Playground Range",
        "features": "Classic, Aesthetic: Natural-looking, safe products fitting for community spaces.",
        "description": "Our wooden playground range is ideal for natural environments."
      },
      "metal": {
        "title": "Metal Playground Range",
        "features": "Modern, Robust: Long-lasting, weather-resistant elements with minimal maintenance.",
        "description": "Our metal playground range represents innovation and durability."
      },
      "conclusion": "We manufacture both types, guaranteeing the best price-to-value ratio and flexible solutions, whether for custom wooden playground elements or robust metal playground equipment."
    },
    "CTA": {
      "title_part1": "Ready to Plan?",
      "title_part2": "Let's Realize Your Vision.",
      "description": "Request a free on-site assessment, and we will help you select the equipment that best fits the area and budget.",
      "primary_btn": "Get a Free Quote",
      "secondary_btn": "View References"
    }
  },
  "ServicesPage": {
    "Hero": {
      "title": "From Design to Turnkey Delivery.",
      "subtitle": "Comprehensive playground construction and maintenance in one hand. We take the burden off your shoulders so you can simply enjoy the result.",
      "cta": "Request a Quote for Your Project"
    },
    "Workflow": {
      "title": "How We Work?",
      "subtitle": "Transparent process, predictable deadlines.",
      "steps": [
        {
          "title": "1. Assessment",
          "description": "We assess the site conditions and your needs during a personal visit."
        },
        {
          "title": "2. Design",
          "description": "We create visual plans considering safety zones and budget constraints."
        },
        {
          "title": "3. Manufacturing",
          "description": "We manufacture certified equipment in our own facility using premium materials."
        },
        {
          "title": "4. Installation",
          "description": "Professional installation, impact-absorbing surfacing, and technical handover."
        }
      ]
    },
    "Details": {
      "title": "Terra Forte Bau Complete Playground Solutions",
      "subtitle": "Terra Forte Bau is more than just a playground manufacturer. We are your professional partners throughout the entire process: from design and construction to grant consultancy. Our management has been guaranteeing high professional quality since 1996, ensuring your project is in the best hands.",
      "Production": {
        "title": "Playground Design & Manufacturing",
        "description": "Design of unique wooden and metal playground elements meeting the highest EU standards. Thanks to our manufacturing capacity, we guarantee the quality of raw materials (natural wood and durable metal) and compliance with standards. We assist in developing aesthetic wooden playground plans that blend into the environment or modern, low-maintenance metal playground concepts.",
        "features": [
          "MSZ EN 1176 standard compliant design",
          "Premium wood and durable metal construction",
          "Custom concepts with manufacturer warranty"
        ]
      },
      "Consulting": {
        "title": "Tender Consulting & Documentation",
        "description": "Greatly facilitating the work of our public sector partners! Our experts help compile complex professional material for playground tenders, budget planning, and preparing necessary technical documentation. Maximize your chances of successful funding with our management-level experience gathered since 1996.",
        "features": [
          "Compilation of complex tender documentation",
          "Preparation of technical plans and budgets",
          "Expert support for successful funding"
        ]
      },
      "Installation": {
        "title": "Delivery & Professional Installation",
        "description": "Fast, precise, and standard-compliant installation of manufactured elements. We work only with accredited, experienced teams, guaranteeing immediate compliance with safety standards.",
        "features": [
          "Installation by accredited professionals",
          "Fast and standard-compliant execution",
          "Guaranteed immediate certification"
        ]
      },
      "Audit": {
        "title": "Post-Installation Safety Audit & Consulting",
        "description": "Our company assists in the safety inspection (MSZ EN 1176) of existing or newly handed-over playgrounds. Precise advice on correcting deficiencies and ensuring safe operation.",
        "badge": "Featured Service",
        "features": [
          "MSZ EN 1176 safety audit",
          "Identification and correction of deficiencies",
          "Safe operation consulting"
        ]
      }
    },
    "FAQ": {
      "title": "Frequently Asked Questions about Construction",
      "items": [
        {
          "question": "How long does the design and construction of a turnkey playground take?",
          "answer": "Thanks to our in-house manufacturing capacity, the process is fast and predictable. From the free needs assessment and visual design to manufacturing and technical handover, the project usually takes 4-8 weeks, depending on the size of the area and the type of equipment chosen (wood or metal)."
        },
        {
          "question": "Can you help with documentation for the Hungarian Village Program or other grants?",
          "answer": "Yes, this is one of our priority services. Our experts, with experience since 1996, compile the complex technical documentation, detailed budget, and visual designs required for winning applications, thereby maximizing the chances of municipalities and institutions securing funding."
        },
        {
          "question": "Why is the MSZ EN 1176 compliance audit necessary, and how do you help?",
          "answer": "The compliance audit is a strict legal requirement for every public playground to ensure children's safety. Our company, working with accredited partners, not only performs the post-installation inspection but also provides concrete repair proposals and, if requested, fixes the uncovered defects, guaranteeing safe operation."
        },
        {
          "question": "What warranty do you offer on self-manufactured wood and metal playground equipment?",
          "answer": "Since we manufacture our equipment in our own domestic facility using premium materials, we offer a comprehensive manufacturer's warranty and long-term spare parts supply. Our metal equipment is maintenance-free and vandal-proof, while our wooden toys ensure weather resistance and durability through special surface treatment."
        }
      ]
    },
    "CTA": {
      "title": "Do you have an idea?",
      "subtitle": "Or are you still looking for a solution? Contact us, and we will help!",
      "btn": "Get a Quote Now"
    }
  },
  "FAQPage": {
    "Hero": {
      "title": "Frequently Asked Questions",
      "subtitle": "Everything worth knowing about playground construction, standards, and maintenance."
    },
    "categories": {
      "general": "General & Ordering",
      "safety": "Safety & Standards",
      "installation": "Construction & Installation",
      "maintenance": "Warranty & Maintenance",
      "tenders": "Grants & Documentation",
      "products": "Wood & Metal Products",
      "private": "For Private Individuals"
    },
    "items": {
      "general": [
        {
          "question": "What is the difference between Terra Forte Bau's manufacturing quality and reseller products?",
          "answer": "As a manufacturer, we exercise full control from raw materials (wood and metal) to the final product, resulting in better quality, flexibility, and price-to-value ratio."
        },
        {
          "question": "What does Terra Forte Bau's leadership-level experience since 1996 mean?",
          "answer": "It means we know the development of the Hungarian market, the legal background, and the specifics of public procurement from the last 25+ years."
        },
        {
          "question": "How long does it take to complete the playground from order to installation?",
          "answer": "The deadline depends on the size of the project and custom manufacturing needs. Due to our manufacturing background, we can undertake faster and more precise scheduling than the market average."
        },
        {
          "question": "Why should I request a quote directly from the playground manufacturer rather than a reseller?",
          "answer": "A quote requested from the manufacturer ensures the best price-to-value ratio, comprehensive warranty, and the flexibility of custom manufacturing."
        },
        {
          "question": "Why is Terra Forte Bau's long-term professional partnership beneficial for municipalities?",
          "answer": "We provide continuous professional advice, assistance with maintenance plans, and ongoing monitoring of grant opportunities."
        }
      ],
      "tenders": [
        {
          "question": "How does Terra Forte Bau help in writing playground grant applications?",
          "answer": "We take the burden off you! We prepare the entire professional material for the applications (plans, technical description, budget), greatly easing municipal administration."
        },
        {
          "question": "What should I do if my playground grant application failed due to professional errors?",
          "answer": "Contact us immediately! We review the faulty application and help prepare professionally impeccable documentation for the next round of applications."
        },
        {
          "question": "How long does it take to compile grant documentation with Terra Forte Bau's help?",
          "answer": "It depends on the complexity of the project, but thanks to professional consultancy, this phase is significantly shortened; you can be ready to submit the application within weeks."
        }
      ],
      "products": [
        {
          "question": "Why is it worth choosing metal playground elements for public spaces today?",
          "answer": "Metal playgrounds are more economical in the long run due to extreme durability and minimal maintenance needs. They are highly resistant to vandalism and weather."
        },
        {
          "question": "How can a wooden playground fit into a modern urban environment without looking outdated?",
          "answer": "Wood's greatest strength is blending into the environment. With modern design and high-quality laminated timber, an aesthetically valuable and durable wooden playground can be created."
        },
        {
          "question": "What lifespan can we expect for Terra Forte Bau metal playground equipment?",
          "answer": "The lifespan of metal playground equipment equipped with anti-corrosion coating can exceed 20 years with proper installation, with minimal depreciation."
        },
        {
          "question": "How are Terra Forte Bau wooden playground elements treated for durability?",
          "answer": "Outdoor wooden playground equipment is made with durable pressure impregnation, which provides effective protection against fungi and insects."
        },
        {
          "question": "How does the price-to-value ratio of a metal playground compare to a wooden one?",
          "answer": "The initial investment for a metal playground may be higher, but due to low maintenance costs and longer lifespan, its long-term price-to-value ratio is much more favorable."
        },
        {
          "question": "Why is it important to incorporate movement-developing metal playground elements?",
          "answer": "Modern metal playground equipment, with its more stable structure, allows for more complex forms of movement, supporting children's motor and cognitive skills."
        },
        {
          "question": "Are Terra Forte Bau playgrounds eco-friendly?",
          "answer": "Yes. Our wooden playground products come from certified sources, and the long lifespan of metal playground elements also supports sustainability."
        },
        {
          "question": "Can the design of a metal playground become outdated?",
          "answer": "We design modern metal playground elements with timeless, clean designs that remain aesthetic even after years, avoiding the risk of obsolescence."
        },
        {
          "question": "Is it possible to replace old, outdated wooden playground elements with metal ones?",
          "answer": "Yes, Terra Forte Bau undertakes the assessment and demolition of existing, outdated wooden playground elements and their replacement with modern, durable metal playground equipment."
        },
        {
          "question": "What colors are available for metal playground equipment?",
          "answer": "Metal playground elements are available in almost any RAL color, so they can be perfectly matched to the environment or the settlement's image."
        }
      ],
      "safety": [
        {
          "question": "Which standard applies to public playgrounds in Hungary?",
          "answer": "The MSZ EN 1176 standard series applies to the design, manufacture, and operation of public playgrounds."
        },
        {
          "question": "How does Terra Forte Bau help prevent vandalism on playgrounds?",
          "answer": "Massive metal playground elements are the most resistant. Additionally, open design and community involvement also reduce the chance of vandalism."
        },
        {
          "question": "What legal risks does operating a non-standard playground entail?",
          "answer": "Significant fines, obligation to close, and liability for damages in case of a serious accident. Compliance with standards (MSZ EN 1176) is critical."
        }
      ],
      "installation": [
        {
          "question": "What documents need to be submitted upon playground handover?",
          "answer": "The declaration of conformity issued by the manufacturer, the installation log, the safety certificate, and the certification of the installed impact protection."
        },
        {
          "question": "What fall protection solution is recommended under a metal playground?",
          "answer": "Due to decreasing maintenance needs, rubber tiles or poured rubber are the most popular and cleanest solutions under metal playgrounds."
        },
        {
          "question": "Is it possible to design a custom, site-specific playground?",
          "answer": "Yes, as a manufacturer, we are flexible. We create wooden and metal playground plans tailored to the site conditions and client needs."
        },
        {
          "question": "How much area is needed to create a standard playground?",
          "answer": "This largely depends on the critical fall area of the equipment. Our experts help with precise area calculation during the design phase."
        },
        {
          "question": "What is the best ground cover under a wooden playground if blending into the environment is the goal?",
          "answer": "Under a wooden playground, wood chips or bark mulch best preserve the natural appearance and blending into the environment."
        }
      ],
      "maintenance": [
        {
          "question": "How necessary is the annual maintenance of wooden playgrounds for municipalities?",
          "answer": "It is essential. If annual care of wooden playground elements is neglected, the lifespan decreases drastically, and the risk of non-compliance fines increases."
        },
        {
          "question": "Do you offer a warranty on installation and products?",
          "answer": "Yes, as a manufacturer, we guarantee the proper functioning of the wooden and metal playground equipment we install, as well as the professionalism of the installation."
        },
        {
          "question": "What is the difference between an operator inspection and a compliance inspection?",
          "answer": "A compliance inspection examines adherence to regulations (e.g., MSZ EN 1176), while an operator inspection focuses on daily, weekly, and monthly maintenance tasks."
        },
        {
          "question": "How resistant are metal playground equipment to graffiti?",
          "answer": "Due to modern coatings, cleaning metal playground elements is easier. Paint can be removed more easily with special cleaners than from untreated wood surfaces."
        }
      ],
      "private": [
        {
          "question": "What criteria should I use to choose a garden playground?",
          "answer": "The most important criteria: the child's age, available space, chosen material (wood aesthetics vs. metal durability), and safety ratings."
        },
        {
          "question": "Do Terra Forte Bau garden playground elements meet any safety regulations?",
          "answer": "Although private garden playgrounds are legally exempt from MSZ EN 1176, as a manufacturer, we design and produce our products according to the highest safety principles."
        },
        {
          "question": "How complicated is it to assemble a Terra Forte Bau wooden playground at home?",
          "answer": "We provide detailed assembly instructions with the products, but for stability and safety, we recommend installation by a professional."
        },
        {
          "question": "When is it better to choose a durable metal swing over wood for the garden?",
          "answer": "If long lifespan, minimal maintenance, and total resistance to weather are the main considerations, choose metal playground elements."
        },
        {
          "question": "What ground cover do you recommend under a garden playground?",
          "answer": "Sand, bark mulch, or rubber tiles. The key is that the ground should be soft under the critical fall height."
        },
        {
          "question": "Where can I see Terra Forte Bau wooden and metal playground products?",
          "answer": "Currently, you can find our latest wooden and metal playground solutions in our catalogs. Contact us for demonstration opportunities!"
        },
        {
          "question": "How often should a wooden garden playground be treated?",
          "answer": "Outdoor wooden playground elements should be treated once a year with glaze or oil to protect the wood material."
        },
        {
          "question": "Is there a warranty on garden playground equipment?",
          "answer": "Yes, as a manufacturer, we offer a warranty on material quality and manufacturing defects."
        },
        {
          "question": "How flammable is a wooden playground?",
          "answer": "The wood materials used are not non-combustible, but special treatment and outdoor placement moderate the fire risk."
        },
        {
          "question": "What is the safest anchoring method for a swing set in the garden?",
          "answer": "The most stable is concreted, in-ground metal leg anchoring, which the manufacturer provides with the product."
        },
        {
          "question": "At what price is a complete garden playground available at Terra Forte Bau?",
          "answer": "Prices depend on the number of selected devices (wood or metal), size, and type of fall protection. Request a custom quote!"
        },
        {
          "question": "Is there a difference between the quality of Terra Forte Bau and import playground elements?",
          "answer": "As a manufacturer, we optimize for Hungarian climatic conditions and strict standards during both raw material selection and processing."
        },
        {
          "question": "For what age categories are playground equipment available?",
          "answer": "Our range includes products for babies (1-3 years), toddlers (3-6 years), and older children (6-12 years)."
        },
        {
          "question": "Is a permit required to set up a garden playground?",
          "answer": "Generally not, but for large, complex structures, it may be worth consulting the local building authority."
        },
        {
          "question": "Does a metal playground get too hot in the summer?",
          "answer": "The outdoor coatings used reduce heat absorption, but in summer heat, it is advisable to use all playground elements (wood and metal) in the shade or in the morning."
        },
        {
          "question": "Is it worth covering wooden playground elements for winter?",
          "answer": "To increase durability, it is recommended to store removable elements (e.g., swing seats) for the winter."
        },
        {
          "question": "What happens if a Terra Forte Bau playground element gets damaged?",
          "answer": "As a manufacturer, we can provide spare parts, which is often an unsolvable problem with non-manufacturer products."
        },
        {
          "question": "Which is more durable: a plastic slide or a metal slide for a garden playground?",
          "answer": "A professional stainless steel slide is much more durable and resistant to UV radiation and cracking than most plastics."
        },
        {
          "question": "How important is replacing playground sand for private individuals?",
          "answer": "Due to hygiene, it is recommended to replenish lost sand with fresh, filtered sand annually."
        },
        {
          "question": "What to do in case of an accident on a private playground?",
          "answer": "Keeping a maintenance log and adhering to Terra Forte Bau safety regulations can reduce risk. In case of a serious accident, a professional should be called to inspect the equipment."
        }
      ]
    },
    "CTA": {
      "title": "Didn't find the answer?",
      "subtitle": "For immediate assistance, look for Hanna AI Assistant in the bottom right corner, answering your questions 24/7!",
      "subtitle2": "If you have a more complex project or require expert consultation, our team is also happy to be at your disposal.",
      "btn": "Personal Contact"
    }
  },
  "LegalPages": {
    "Privacy": {
      "title": "Privacy Policy",
      "lastUpdated": "Last updated: February 20, 2025",
      "intro": {
        "title": "1. Introduction",
        "content": "Terra Forte Bau Kft. (hereinafter: Data Controller) is committed to protecting the personal data of its customers and website visitors. The purpose of this policy is to transparently explain what data we collect, how we use it, and what rights you have under the GDPR (General Data Protection Regulation)."
      },
      "controller": {
        "title": "2. Data Controller Details",
        "content": "The controller of the data provided on the website:",
        "items": [
          "Company Name: Terra Forte Bau Kft.",
          "Registered Office: 3662, Ózd-Somsályfő Telep 1., Hungary",
          "Registration Number: 05 09 024254",
          "Tax Number: 23954780-2-05",
          "Representative: Attila Döbör, Managing Director",
          "E-mail: info@terrafortebau.hu",
          "Phone: +36 70 369-8193"
        ]
      },
      "data_collection": {
        "title": "3. Scope and Purpose of Data Processing",
        "sections": [
          {
            "subtitle": "Contact and Quote Requests",
            "text": "When you fill out forms on our website, we request the following data to respond and provide a quote:",
            "list": [
              "Name",
              "E-mail address",
              "Phone number",
              "City/Location (for delivery calculation)"
            ]
          },
          {
            "subtitle": "Automatically Collected Data (Cookies)",
            "text": "Our website uses cookies to improve user experience and create traffic statistics. These do not identify you personally."
          }
        ]
      },
      "cookies": {
        "title": "4. Use of Cookies",
        "content": "The website uses essential and analytical cookies.",
        "types": [
          "Essential cookies: The site cannot function properly without these (e.g., language selection).",
          "Analytical cookies (Google Analytics): Help us understand how visitors use the site. Data is anonymized."
        ],
        "note": "You can modify cookie settings in your browser at any time."
      },
      "rights": {
        "title": "5. Your Rights",
        "content": "You have the right to request information about the processing of your personal data, and to request its correction, deletion, or blocking at any time. You can submit your request via any of our contact details."
      },
      "hosting": {
        "title": "6. Data Processors and Hosting",
        "content": "Our website is served by Vercel Inc. Data is stored on secure servers.",
        "details": "Hosting Provider: Vercel Inc. (340 S Lemon Ave #4133 Walnut, CA 91789, USA)"
      }
    },
    "Imprint": {
      "title": "Imprint",
      "subtitle": "Company Information and Legal Notice",
      "provider": {
        "title": "Provider Details",
        "company_label": "Company Name:",
        "company_value": "Terra Forte Bau Kft.",
        "address_label": "Registered Office:",
        "address_value": "3662, Ózd-Somsályfő Telep 1., Hungary",
        "reg_label": "Registration Number:",
        "reg_value": "05 09 024254",
        "tax_label": "Tax Number:",
        "tax_value": "23954780-2-05",
        "rep_label": "Representative:",
        "rep_value": "Attila Döbör, Managing Director"
      },
      "contact": {
        "title": "Contact Details",
        "phone_label": "Phone:",
        "phone_value": "+36 70 369-8193",
        "email_label": "E-mail:",
        "email_value": "info@terrafortebau.hu",
        "web_label": "Web:",
        "web_value": "www.terrafortebau.hu"
      },
      "hosting": {
        "title": "Hosting Provider",
        "name_label": "Name:",
        "name_value": "Vercel Inc.",
        "address_label": "Address:",
        "address_value": "340 S Lemon Ave #4133 Walnut, CA 91789, USA",
        "web_label": "Web:",
        "web_value": "https://vercel.com"
      }
    }
  },
  "CookieBanner": {
    "title": "Privacy Matters",
    "description": "Our website uses cookies and Google Consent Mode v2 technology to improve user experience and analyze traffic. By clicking 'Accept All', you consent to the use of analytical cookies.",
    "accept": "Accept All",
    "decline": "Essential Only",
    "privacy_link": "Privacy Policy"
  },
  "ContactPage": {
    "title": "Get in Touch",
    "description": "Whether you have a specific idea or just need advice, our experts are ready to help. Request a free on-site assessment today!",
    "info": {
      "address_label": "Address",
      "address_value_1": "3662, Ózd-Somsályfő",
      "address_value_2": "Telep 1., Hungary",
      "phone_label": "Phone",
      "phone_value": "+36 70 369-8193",
      "email_label": "Email",
      "email_value": "info@terrafortebau.hu"
    },
    "form": {
      "first_name": "First name",
      "last_name": "Last name",
      "email": "Email address",
      "phone": "Phone number",
      "message": "Message",
      "submit_btn": "Send message",
      "success_title": "Message Sent!",
      "success_desc": "Thank you for contacting us. Our colleague will get back to you shortly.",
      "error_title": "An error occurred",
      "error_desc": "Please try again later or email us directly.",
      "first_name_placeholder": "e.g. John",
      "last_name_placeholder": "e.g. Doe",
      "email_placeholder": "example@email.com",
      "phone_placeholder": "+1 555 000 0000",
      "message_placeholder": "Describe how we can help..."
    }
  },
  "QuotePage": {
    "title": "Request a Quote",
    "description": "Fill out our form, and our experts will contact you within 24 hours with a personalized, no-obligation quote.",
    "form": {
      "personal_title": "Personal Details",
      "project_title": "Project Details",
      "first_name": "First name",
      "last_name": "Last name",
      "email": "Email address",
      "phone": "Phone number",
      "type_label": "Subject of Interest",
      "type_options": {
        "wooden": "Wooden Playground",
        "metal": "Metal Playground",
        "fitness": "Outdoor Fitness",
        "street": "Street Furniture",
        "other": "Other / Mixed"
      },
      "timing_label": "Planned Implementation",
      "timing_options": {
        "asap": "Immediately (Urgent)",
        "1_3_months": "Within 1-3 months",
        "3_6_months": "Within 3-6 months",
        "planning": "Just browsing / Planning phase"
      },
      "message": "Additional Notes / Project Description",
      "submit_btn": "Submit Quote Request",
      "success_title": "Request Sent!",
      "success_desc": "Thank you! Our colleagues will process your request shortly.",
      "error_title": "An error occurred",
      "error_desc": "Please try again later.",
      "first_name_placeholder": "e.g. John",
      "last_name_placeholder": "e.g. Doe",
      "email_placeholder": "example@email.com",
      "phone_placeholder": "+1 555 000 0000",
      "message_placeholder": "Briefly describe your ideas or the area where you plan the playground..."
    }
  },
  "BlogPage": {
    "title": "Blog & News",
    "subtitle": "Professional articles, maintenance tips, and news from the world of playground construction.",
    "posts": [
      {
        "id": 1,
        "title": "How to Choose a Safe Playground?",
        "description": "Child safety comes first. Our expert guide helps you navigate the world of MSZ EN 1176 standards and necessary certifications.",
        "date": "Mar 16, 2025",
        "category": "Advice",
        "author": {
          "name": "József Kiss",
          "role": "CEO"
        }
      },
      {
        "id": "2",
        "title": "Maintenance of Wooden Playgrounds",
        "description": "Natural materials need care. Here is how to preserve the lifespan and beauty of your wooden playground equipment for decades.",
        "date": "Mar 10, 2025",
        "category": "Maintenance",
        "author": {
          "name": "Anna Nagy",
          "role": "Landscape Architect"
        }
      },
      {
        "id": "3",
        "title": "Building Communities with Playgrounds",
        "description": "How does a well-designed playground become the center of the local community? Tips for municipalities and residential communities.",
        "date": "Feb 12, 2025",
        "category": "Planning",
        "author": {
          "name": "Péter Kovács",
          "role": "Project Manager"
        }
      }
    ]
  },
  "ReferencesPage": {
    "title": "Our References",
    "subtitle": "We are proud of our work. Take a look at our selected projects that demonstrate our expertise.",
    "filters": {
      "all": "All",
      "wooden": "Wooden Playgrounds",
      "metal": "Metal Playgrounds",
      "fitness": "Fitness Parks",
      "custom": "Custom Builds"
    },
    "items": [
      {
        "id": 1,
        "title": "City Adventure Park",
        "location": "Budapest, District 18",
        "category": "metal",
        "image": "/Referencia/ref-1.jpg",
        "slug": "varosi-kalandpark-bp18"
      },
      {
        "id": 2,
        "title": "Sunflower Kindergarten",
        "location": "Debrecen",
        "category": "wooden",
        "image": "/Referencia/ref-2.jpeg",
        "slug": "napraforgo-ovoda-debrecen"
      },
      {
        "id": 3,
        "title": "Forest Gym Track",
        "location": "Visegrád",
        "category": "wooden",
        "image": "/Referencia/ref-3.jpg",
        "slug": "erdei-tornapalya-visegrad"
      },
      {
        "id": 4,
        "title": "Knights' Castle Theme Park",
        "location": "Székesfehérvár",
        "category": "custom",
        "image": "/Referencia/ref-4.webp",
        "slug": "lovagvar-tematikus-park"
      }
    ]
  }
}
